importguardian/__init__.py
importguardian/__main__.py
importguardian/importguardian.py
python_import_guardian-0.1.3.dist-info/LICENSE
python_import_guardian-0.1.3.dist-info/METADATA
python_import_guardian-0.1.3.dist-info/WHEEL
python_import_guardian-0.1.3.dist-info/entry_points.txt
python_import_guardian-0.1.3.dist-info/top_level.txt
python_import_guardian-0.1.3.dist-info/RECORD
