Metadata-Version: 2.1
Name: python-import-guardian
Version: 0.1.3
Summary: A static-analysis Python import guardian.
Home-page: https://gitlab.com/gmb/python-import-guardian
Author: Graham Binns
Author-email: graham@outcoded.uk
License: UNKNOWN
Download-URL: https://gitlab.com/gmb/python-import-guardian/-/archive/master/python-import-guardian-master.tar.gz
Keywords: import,guardian,static-analysis
Platform: UNKNOWN
Classifier: Programming Language :: Python :: 3
Classifier: License :: OSI Approved :: MIT License
Classifier: Operating System :: OS Independent
